earthnet/__init__.py
earthnet/coords.py
earthnet/coords_dict.py
earthnet/download.py
earthnet/download_links.py
earthnet/download_v2.py
earthnet/parallel_score.py
earthnet/plot_cube.py
earthnet/score_v2.py
earthnet-0.3.11.dist-info/LICENSE
earthnet-0.3.11.dist-info/METADATA
earthnet-0.3.11.dist-info/WHEEL
earthnet-0.3.11.dist-info/top_level.txt
earthnet-0.3.11.dist-info/RECORD
