Metadata-Version: 2.1
Name: earthnet
Version: 0.3.11
Summary: EarthNet2021 Toolkit: Download, Evaluation, Plotting
Home-page: https://earthnet.tech
Author: Vitus Benson
Author-email: vbenson@bgc-jena.mpg.de
Classifier: Intended Audience :: Science/Research
Classifier: License :: Other/Proprietary License
Classifier: Programming Language :: Python :: 3
License-File: LICENSE
Requires-Dist: numpy
Requires-Dist: scipy
Requires-Dist: scikit-image
Requires-Dist: tqdm
Requires-Dist: fire
Requires-Dist: pyproj
Requires-Dist: pandas
Requires-Dist: s3fs
Requires-Dist: xarray
Requires-Dist: netcdf4
